Compiled from "Ex1.java"
public class tut4.Ex1 {
  public tut4.Ex1();
    Code:
       0: aload_0
       1: invokespecial #8                  // Method java/lang/Object."<init>":()V
       4: return

  public static void main(java.lang.String[]);
    Code:
       0: ldc           #16                 // String class Hello { public static void main(String[] args) {\tSystem.out.println(\"Hello world!\"); } }
       2: astore_1
       3: aload_1
       4: invokestatic  #18                 // Method com/github/javaparser/JavaParser.parse:(Ljava/lang/String;)Lcom/github/javaparser/ast/CompilationUnit;
       7: astore_2
       8: getstatic     #24                 // Field java/lang/System.out:Ljava/io/PrintStream;
      11: aload_2
      12: invokevirtual #30                 // Method java/io/PrintStream.println:(Ljava/lang/Object;)V
      15: return
}
